jobber/__init__.py
jobber/cli.py
jobberr-0.1.0.dist-info/METADATA
jobberr-0.1.0.dist-info/WHEEL
jobberr-0.1.0.dist-info/entry_points.txt
jobberr-0.1.0.dist-info/top_level.txt
jobberr-0.1.0.dist-info/RECORD
