Metadata-Version: 2.4
Name: jobberr
Version: 0.1.0
Summary: run python job
Author: Dyotak
Dynamic: author
Dynamic: description
Dynamic: description-content-type
Dynamic: summary
